alopex-0.3.3.dist-info/METADATA
alopex-0.3.3.dist-info/WHEEL
alopex/__init__.py
alopex/_alopex.abi3.so
alopex/_alopex.pyi
alopex/py.typed
alopex-0.3.3.dist-info/RECORD
