Metadata-Version: 2.4
Name: alopex
Version: 0.3.3
Classifier: Programming Language :: Python :: 3
Classifier: Programming Language :: Rust
Classifier: License :: OSI Approved :: Apache Software License
Requires-Dist: numpy>=1.23 ; extra == 'numpy'
Requires-Dist: polars>=0.20 ; extra == 'polars'
Requires-Dist: numpy>=1.23 ; extra == 'full'
Requires-Dist: polars>=0.20 ; extra == 'full'
Requires-Dist: pytest>=7 ; extra == 'dev'
Requires-Dist: pytest-benchmark>=4 ; extra == 'dev'
Requires-Dist: numpy>=1.23 ; extra == 'dev'
Requires-Dist: polars>=0.20 ; extra == 'dev'
Provides-Extra: numpy
Provides-Extra: polars
Provides-Extra: full
Provides-Extra: dev
Summary: Python bindings for Alopex DB
Keywords: database,vector,bindings
License: Apache-2.0
Requires-Python: >=3.8
